virtualenvwrapper.django-0.4.1-py2.7-nspkg.pth
virtualenvwrapper/django_project.py
virtualenvwrapper.django-0.4.1.dist-info/DESCRIPTION.rst
virtualenvwrapper.django-0.4.1.dist-info/entry_points.txt
virtualenvwrapper.django-0.4.1.dist-info/METADATA
virtualenvwrapper.django-0.4.1.dist-info/metadata.json
virtualenvwrapper.django-0.4.1.dist-info/namespace_packages.txt
virtualenvwrapper.django-0.4.1.dist-info/RECORD
virtualenvwrapper.django-0.4.1.dist-info/top_level.txt
virtualenvwrapper.django-0.4.1.dist-info/WHEEL
