Metadata-Version: 2.0
Name: virtualenvwrapper.django
Version: 0.4.1
Summary: virtualenvwrapper plugin to create a Django project work directory
Home-page: https://bitbucket.org/dhellmann/virtualenvwrapper.django
Author: Doug Hellmann
Author-email: doug.hellmann@gmail.com
License: UNKNOWN
Platform: Any
Classifier: Development Status :: 3 - Alpha
Classifier: License :: OSI Approved :: BSD License
Classifier: Intended Audience :: Developers
Classifier: Environment :: Console
Classifier: Framework :: Django
Classifier: Programming Language :: Python :: 2
Classifier: Programming Language :: Python :: 2.6
Classifier: Programming Language :: Python :: 2.7
Classifier: Programming Language :: Python :: 3
Classifier: Programming Language :: Python :: 3.2
Classifier: Programming Language :: Python :: 3.3
Requires: virtualenv
Requires: virtualenvwrapper (>=4.0)
Provides: virtualenvwrapper.django
